mopidy_marceline/__init__.py
mopidy_marceline/ext.conf
mopidy_marceline/static/index.html
mopidy_marceline/static/logo-16.webp
mopidy_marceline/static/logo-192.webp
mopidy_marceline/static/logo-32.webp
mopidy_marceline/static/logo-512.webp
mopidy_marceline/static/logo-apple.webp
mopidy_marceline/static/logo-mask.webp
mopidy_marceline/static/logo.ico
mopidy_marceline/static/logo.svg
mopidy_marceline/static/manifest.webmanifest
mopidy_marceline/static/_app/env.js
mopidy_marceline/static/_app/version.json
mopidy_marceline/static/_app/immutable/assets/0.Dg4n2ZO7.css
mopidy_marceline/static/_app/immutable/assets/Link.opm6E88t.css
mopidy_marceline/static/_app/immutable/assets/material-symbols-outlined.Dg9NVvbp.woff2
mopidy_marceline/static/_app/immutable/chunks/B6q3kgX-.js
mopidy_marceline/static/_app/immutable/chunks/BayFEZB_.js
mopidy_marceline/static/_app/immutable/chunks/Bouf9AsO.js
mopidy_marceline/static/_app/immutable/chunks/BwpGZfim.js
mopidy_marceline/static/_app/immutable/chunks/Byt18mut.js
mopidy_marceline/static/_app/immutable/chunks/C4aLToA0.js
mopidy_marceline/static/_app/immutable/chunks/C58asskQ.js
mopidy_marceline/static/_app/immutable/chunks/C659k8ar.js
mopidy_marceline/static/_app/immutable/chunks/CICL-Sq2.js
mopidy_marceline/static/_app/immutable/chunks/CPG7K0kl.js
mopidy_marceline/static/_app/immutable/chunks/CRpwIFV_.js
mopidy_marceline/static/_app/immutable/chunks/CUMWwcMq.js
mopidy_marceline/static/_app/immutable/chunks/CYTYGeBy.js
mopidy_marceline/static/_app/immutable/chunks/CrbyPaqk.js
mopidy_marceline/static/_app/immutable/chunks/D0Gr7Hm0.js
mopidy_marceline/static/_app/immutable/chunks/DDL4Vd-v.js
mopidy_marceline/static/_app/immutable/chunks/DHUdjfhY.js
mopidy_marceline/static/_app/immutable/chunks/DK3wCkEE.js
mopidy_marceline/static/_app/immutable/chunks/DKQz3N_7.js
mopidy_marceline/static/_app/immutable/chunks/Db-C4wSA.js
mopidy_marceline/static/_app/immutable/chunks/Ddm0HaqK.js
mopidy_marceline/static/_app/immutable/chunks/DgqPUcrR.js
mopidy_marceline-0.0.5.dist-info/licenses/LICENSE
mopidy_marceline-0.0.5.dist-info/METADATA
mopidy_marceline-0.0.5.dist-info/WHEEL
mopidy_marceline-0.0.5.dist-info/entry_points.txt
mopidy_marceline-0.0.5.dist-info/top_level.txt
mopidy_marceline-0.0.5.dist-info/RECORD
