Metadata-Version: 2.4
Name: Mopidy-Marceline
Version: 0.0.5
Summary: Mopidy extension with stylish frontend for controlling playback and browsing
Author-email: João Pereira <me@toino.pt>
License-Expression: GPL-3.0-or-later
Project-URL: Repository, https://github.com/ttoino/mopidy-marceline
Classifier: Environment :: No Input/Output (Daemon)
Classifier: Intended Audience :: End Users/Desktop
Classifier: Operating System :: OS Independent
Classifier: Topic :: Multimedia :: Sound/Audio :: Players
Requires-Python: >=3.11
License-File: LICENSE
Requires-Dist: mopidy>=3.4.1
Requires-Dist: pykka>=3.1.1
Dynamic: license-file
